quantpy/__init__.py
quantpy/conftest.py
quantpy/release.py
quantpy/ising/qubo.py
quantpy/ising/sqa.py
quantpy/sympy/__init__.py
quantpy/sympy/expr_extension.py
quantpy/sympy/gate_extension.py
quantpy/sympy/qapply.py
quantpy/sympy/executor/__init__.py
quantpy/sympy/executor/_base_quantum_executor.py
quantpy/sympy/executor/classical_simulation_executor.py
quantpy/sympy/executor/ibmq_executor.py
quantpy/sympy/executor/sympy_executor.py
quantpy/sympy/executor/simulator/__init__.py
quantpy/sympy/executor/simulator/_base_simulator.py
quantpy/sympy/executor/simulator/numpy_simulator.py
quantpy-0.0.2.dev12.dist-info/AUTHORS
quantpy-0.0.2.dev12.dist-info/LICENSE
quantpy-0.0.2.dev12.dist-info/METADATA
quantpy-0.0.2.dev12.dist-info/WHEEL
quantpy-0.0.2.dev12.dist-info/top_level.txt
quantpy-0.0.2.dev12.dist-info/RECORD
