Metadata-Version: 2.1
Name: quantpy
Version: 0.0.2.dev12
Summary: Quantum Computer system in Python
Home-page: http://quantpy.org
Author: QuantPy development team
Author-email: quantpy@openql.org
License: BSD-3-Clause
Keywords: Math Physics
Platform: UNKNOWN
Classifier: License :: OSI Approved :: BSD License
Classifier: Operating System :: OS Independent
Classifier: Programming Language :: Python
Classifier: Topic :: Scientific/Engineering
Classifier: Topic :: Scientific/Engineering :: Mathematics
Classifier: Topic :: Scientific/Engineering :: Physics
Classifier: Programming Language :: Python :: 3.5
Classifier: Programming Language :: Python :: 3.6
Requires-Python: >=3.5
Requires-Dist: numpy
Requires-Dist: qiskit (==0.11.1)
Requires-Dist: sympy (==1.4)
